odoo8_addon_contract_show_recurring_invoice-8.0.1.0.0.99.dev26-py3.8-nspkg.pth
odoo_addons/contract_show_recurring_invoice/README.rst
odoo_addons/contract_show_recurring_invoice/__init__.py
odoo_addons/contract_show_recurring_invoice/__openerp__.py
odoo_addons/contract_show_recurring_invoice/i18n/ar.po
odoo_addons/contract_show_recurring_invoice/i18n/bg.po
odoo_addons/contract_show_recurring_invoice/i18n/bs.po
odoo_addons/contract_show_recurring_invoice/i18n/ca.po
odoo_addons/contract_show_recurring_invoice/i18n/contract_show_recurring_invoice.pot
odoo_addons/contract_show_recurring_invoice/i18n/cs.po
odoo_addons/contract_show_recurring_invoice/i18n/de.po
odoo_addons/contract_show_recurring_invoice/i18n/el_GR.po
odoo_addons/contract_show_recurring_invoice/i18n/en_GB.po
odoo_addons/contract_show_recurring_invoice/i18n/es.po
odoo_addons/contract_show_recurring_invoice/i18n/es_CR.po
odoo_addons/contract_show_recurring_invoice/i18n/es_EC.po
odoo_addons/contract_show_recurring_invoice/i18n/es_MX.po
odoo_addons/contract_show_recurring_invoice/i18n/es_PE.po
odoo_addons/contract_show_recurring_invoice/i18n/et.po
odoo_addons/contract_show_recurring_invoice/i18n/fi.po
odoo_addons/contract_show_recurring_invoice/i18n/fr.po
odoo_addons/contract_show_recurring_invoice/i18n/fr_CA.po
odoo_addons/contract_show_recurring_invoice/i18n/fr_CH.po
odoo_addons/contract_show_recurring_invoice/i18n/gl.po
odoo_addons/contract_show_recurring_invoice/i18n/hr.po
odoo_addons/contract_show_recurring_invoice/i18n/hr_HR.po
odoo_addons/contract_show_recurring_invoice/i18n/hu.po
odoo_addons/contract_show_recurring_invoice/i18n/id.po
odoo_addons/contract_show_recurring_invoice/i18n/it.po
odoo_addons/contract_show_recurring_invoice/i18n/ja.po
odoo_addons/contract_show_recurring_invoice/i18n/lt.po
odoo_addons/contract_show_recurring_invoice/i18n/mk.po
odoo_addons/contract_show_recurring_invoice/i18n/mn.po
odoo_addons/contract_show_recurring_invoice/i18n/nb.po
odoo8_addon_contract_show_recurring_invoice-8.0.1.0.0.99.dev26.dist-info/METADATA
odoo8_addon_contract_show_recurring_invoice-8.0.1.0.0.99.dev26.dist-info/WHEEL
odoo8_addon_contract_show_recurring_invoice-8.0.1.0.0.99.dev26.dist-info/namespace_packages.txt
odoo8_addon_contract_show_recurring_invoice-8.0.1.0.0.99.dev26.dist-info/top_level.txt
odoo8_addon_contract_show_recurring_invoice-8.0.1.0.0.99.dev26.dist-info/RECORD
